quarto_batch_convert/__init__.py
quarto_batch_convert/quarto_batch_convert.py
quarto_batch_convert-2025.9.1.dist-info/licenses/LICENSE.txt
quarto_batch_convert-2025.9.1.dist-info/WHEEL
quarto_batch_convert-2025.9.1.dist-info/entry_points.txt
quarto_batch_convert-2025.9.1.dist-info/METADATA
quarto_batch_convert-2025.9.1.dist-info/RECORD
