Metadata-Version: 2.4
Name: quarto-batch-convert
Version: 2025.9.1
Summary: Converts multiple Jupyter notebooks to Quarto documents at once
Keywords: quarto,jupyter,notebook,converter,cli
License-Expression: MIT
License-File: LICENSE.txt
Classifier: Programming Language :: Python :: 3
Classifier: License :: OSI Approved :: MIT License
Classifier: Operating System :: OS Independent
Requires-Dist: click==8.1.3
Requires-Python: >=3.13
Project-URL: Homepage, https://github.com/kompre/quarto_batch_convert
